{
  "name": "my-money",
  "version": "1.0.0",
  "description": "Projeto front em React, backend em graphql, com api rest",
  "main": "index.js",
  "scripts": {
    "start": "node src/index",
    "test": "echo \"Error: no test specified\" && exit 1",
    "lint": "eslint --fix \"./{src,client/src}/**/*.js\"",
    "prettier": "prettier --write\"./{src,client/src}/**/*.{js,scss}\""
  },
  "repository": {
    "type": "git",
    "url": "git+https://github.com/ederpbj/my-money.git"
  },
  "keywords": [],
  "author": "",
  "license": "ISC",
  "bugs": {
    "url": "https://github.com/ederpbj/my-money/issues"
  },
  "homepage": "https://github.com/ederpbj/my-money#readme",
  "devDependencies": {
    "eslint": "^6.8.0",
    "eslint-config-prettier": "^6.9.0",
    "eslint-plugin-node": "^11.0.0",
    "prettier": "^1.19.1"
  },
  "dependencies": {
    "express": "^4.17.1"
  }
}
